hydrocrypto-0.2.1.dist-info/METADATA
hydrocrypto-0.2.1.dist-info/WHEEL
hydrocrypto-0.2.1.dist-info/license_files/LICENSE
hydrocrypto/__init__.py
hydrocrypto/hydrocrypto.cpython-39-s390x-linux-gnu.so
hydrocrypto-0.2.1.dist-info/RECORD
