Metadata-Version: 2.1
Name: hydrocrypto
Version: 0.2.1
Classifier: Development Status :: 4 - Beta
Classifier: Topic :: Security :: Cryptography
Classifier: Programming Language :: Rust
Classifier: Programming Language :: Python :: Implementation :: CPython
Classifier: Programming Language :: Python :: Implementation :: PyPy
Classifier: Programming Language :: Python :: 3
Classifier: Programming Language :: Python :: 3.8
Classifier: Programming Language :: Python :: 3.9
Classifier: Programming Language :: Python :: 3.10
Classifier: Programming Language :: Python :: 3.11
Classifier: License :: OSI Approved :: GNU Lesser General Public License v3 (LGPLv3)
License-File: LICENSE
Summary: Cryptography Extension for Hydrogram
Keywords: telegram crypto cryptography mtproto aes
Author-email: Anand <anandpskerala@gmail.com>
License: LGPL-3.0-or-later
Requires-Python: >=3.8
